Workbook
Name Capex: Inputs!$B$3
Name Price: Inputs!$B$4
Name Opex: Inputs!$B$5
Name Royalty: Inputs!$B$6
Name TaxRate: Inputs!$B$7
Name DiscountRate: Inputs!$B$8
Name Debt: Inputs!$B$9
Name InterestRate: Inputs!$B$10

Sheet Inputs
A1: Project economics inputs
A3: Capex ($MM) | B3: 250
A4: Oil price ($/bbl) | B4: =[1]Deck!$B$2 -> 70
A5: Opex ($MM/yr) | B5: 8
A6: Royalty rate | B6: 0.125
A7: Tax rate | B7: 0.25
A8: Discount rate | B8: 0.1
A9: Debt amount ($MM) | B9: 100
A10: Interest rate | B10: 0.07

Sheet Profile
A1: Production profile
A3: Year | B3: 1 | C3: 2 | D3: 3 | E3: 4 | F3: 5 | G3: 6 | H3: 7 | I3: 8 | J3: 9 | K3: 10
A4: Production (MMbbl) | B4: 2 | C4: 3.5 | D4: 3.2 | E4: 2.8 | F4: 2.4 | G4: 2 | H4: 1.7 | I4: 1.4 | J4: 1.2 | K4: 1

Sheet Cashflow
A1: Cash flow
A3: Year | C3: =Profile!B3 -> 1 | D3: =Profile!C3 -> 2 | E3: =Profile!D3 -> 3 | F3: =Profile!E3 -> 4 | G3: =Profile!F3 -> 5 | H3: =Profile!G3 -> 6 | I3: =Profile!H3 -> 7 | J3: =Profile!I3 -> 8 | ... L3: =Profile!K3 -> 10
A4: Production (MMbbl) | C4: =Profile!B4 -> 2 | D4: =Profile!C4 -> 3.5 | E4: =Profile!D4 -> 3.2 | F4: =Profile!E4 -> 2.8 | G4: =Profile!F4 -> 2.4 | H4: =Profile!G4 -> 2 | I4: =Profile!H4 -> 1.7 | J4: =Profile!I4 -> 1.4 | ... L4: =Profile!K4 -> 1
A5: Revenue ($MM) | C5: =C4*Price -> 140 | D5: =D4*Price -> 245 | E5: =E4*Price -> 224 | F5: =F4*Price -> 196 | G5: =G4*Price -> 168 | H5: =H4*Price -> 140 | I5: =I4*Price -> 119 | J5: =J4*Price -> 98 | ... L5: =L4*Price -> 70
A6: Royalty ($MM) | C6: =C5*0.125 -> 17.5 | D6: =D5*0.125 -> 30.625 | E6: =E5*0.125 -> 28 | F6: =F5*0.125 -> 24.5 | G6: =G5*0.125 -> 21 | H6: =H5*0.125 -> 17.5 | I6: =I5*0.125 -> 14.875 | J6: =J5*0.125 -> 12.25 | ... L6: =L5*0.125 -> 8.75
A7: Opex ($MM) | C7: =Opex -> 8 | D7: =Opex -> 8 | E7: =Opex -> 8 | F7: =Opex -> 8 | G7: =Opex -> 8 | H7: =Opex -> 8 | I7: =Opex -> 8 | J7: =Opex -> 8 | ... L7: =Opex -> 8
A8: Opening debt ($MM) | C8: =Debt -> 100 | D8: =C11 -> 55.984801 | E8: =D11 -> 0 | F8: =E11 -> 0 | G8: =F11 -> 0 | H8: =G11 -> 0 | I8: =H11 -> 0 | J8: =I11 -> 0 | K8: =J11 -> 0 | L8: =K11 -> 0
A9: Interest ($MM) | C9: =InterestRate*(C8+C11)/2 -> 5.459468 | D9: =InterestRate*(D8+D11)/2 -> 1.959468 | E9: =InterestRate*(E8+E11)/2 -> 0 | F9: =InterestRate*(F8+F11)/2 -> 0 | G9: =InterestRate*(G8+G11)/2 -> 0 | H9: =InterestRate*(H8+H11)/2 -> 0 | I9: =InterestRate*(I8+I11)/2 -> 0 | J9: =InterestRate*(J8+J11)/2 -> 0 | ... L9: =InterestRate*(L8+L11)/2 -> 0
A10: Cash available for debt ($MM) | C10: =C5-C6-C7-C9-C13 -> 88.030399 | D10: =D5-D6-D7-D9-D13 -> 159.56165 | E10: =E5-E6-E7-E9-E13 -> 147.25 | F10: =F5-F6-F7-F9-F13 -> 128.875 | G10: =G5-G6-G7-G9-G13 -> 110.5 | H10: =H5-H6-H7-H9-H13 -> 79.5 | I10: =I5-I6-I7-I9-I13 -> 78.34375 | J10: =J5-J6-J7-J9-J13 -> 64.5625 | ... L10: =L5-L6-L7-L9-L13 -> 46.1875
A11: Closing debt ($MM) | C11: =MAX(0,C8-MIN(C8,MAX(0,C10)*0.5)) -> 55.984801 | D11: =MAX(0,D8-MIN(D8,MAX(0,D10)*0.5)) -> 0 | E11: =MAX(0,E8-MIN(E8,MAX(0,E10)*0.5)) -> 0 | F11: =MAX(0,F8-MIN(F8,MAX(0,F10)*0.5)) -> 0 | G11: =MAX(0,G8-MIN(G8,MAX(0,G10)*0.5)) -> 0 | H11: =MAX(0,H8-MIN(H8,MAX(0,H10)*0.5)) -> 0 | I11: =MAX(0,I8-MIN(I8,MAX(0,I10)*0.5)) -> 0 | J11: =MAX(0,J8-MIN(J8,MAX(0,J10)*0.5)) -> 0 | ... L11: =MAX(0,L8-MIN(L8,MAX(0,L10)*0.5)) -> 0
A12: Taxable income ($MM) | C12: =C5-C6-C7-C9-Capex/10 -> 84.040532 | D12: =D5-D6-D7-D9-Capex/10 -> 179.41553 | E12: =E5-E6-E7-E9-Capex/10 -> 163 | F12: =F5-F6-F7-F9-Capex/10 -> 138.5 | G12: =G5-G6-G7-G9-Capex/10 -> 114 | H12: =H5-H6-H7-H9-Capex/10 -> 89.5 | I12: =I5-I6-I7-I9-Capex/10 -> 71.125 | J12: =J5-J6-J7-J9-Capex/10 -> 52.75 | ... L12: =L5-L6-L7-L9-Capex/10 -> 28.25
A13: Tax ($MM) | C13: =MAX(0,C12)*TaxRate -> 21.010133 | D13: =MAX(0,D12)*TaxRate -> 44.853883 | E13: =MAX(0,E12)*TaxRate -> 40.75 | F13: =MAX(0,F12)*TaxRate -> 34.625 | G13: =MAX(0,G12)*TaxRate -> 28.5 | H13: =MAX(0,H5)*TaxRate -> 35 | I13: =MAX(0,I12)*TaxRate -> 17.78125 | J13: =MAX(0,J12)*TaxRate -> 13.1875 | K13: =MAX(0,K12)*TaxRate -> 10.125 | L13: =MAX(0,L12)*TaxRate -> 7.0625
A14: Net cash flow ($MM) | C14: =C5-C6-C7-C9-C13-(C8-C11)-IF(C3=1,Capex-Debt,0) -> -105.9848 | D14: =D5-D6-D7-D9-D13-(D8-D11)-IF(D3=1,Capex-Debt,0) -> 103.57685 | E14: =E5-E6-E7-E9-E13-(E8-E11)-IF(E3=1,Capex-Debt,0) -> 147.25 | F14: =F5-F6-F7-F9-F13-(F8-F11)-IF(F3=1,Capex-Debt,0) -> 128.875 | G14: =G5-G6-G7-G9-G13-(G8-G11)-IF(G3=1,Capex-Debt,0) -> 110.5 | H14: =H5-H6-H7-H9-H13-(H8-H11)-IF(H3=1,Capex-Debt,0) -> 79.5 | I14: =I5-I6-I7-I9-I13-(I8-I11)-IF(I3=1,Capex-Debt,0) -> 78.34375 | J14: =J5-J6-J7-J9-J13-(J8-J11)-IF(J3=1,Capex-Debt,0) -> 64.5625 | ... L14: =L5-L6-L7-L9-L13-(L8-L11)-IF(L3=1,Capex-Debt,0) -> 46.1875
A15: Discount factor | C15: =1/(1+DiscountRate)^C3 -> 0.90909091 | D15: =1/(1+DiscountRate)^D3 -> 0.82644628 | E15: =1/(1+DiscountRate)^E3 -> 0.7513148 | F15: =1/(1+DiscountRate)^F3 -> 0.68301346 | G15: =1/(1+DiscountRate)^G3 -> 0.62092132 | H15: =1/(1+DiscountRate)^H3 -> 0.56447393 | I15: =1/(1+DiscountRate)^I3 -> 0.51315812 | J15: =1/(1+DiscountRate)^J3 -> 0.46650738 | ... L15: =1/(1+DiscountRate)^L3 -> 0.38554329
A16: Discounted cash flow ($MM) | C16: =C14*C15 -> -96.349819 | D16: =D14*D15 -> 85.600701 | E16: =E14*E15 -> 110.6311 | F16: =F14*F15 -> 88.023359 | G16: =G14*G15 -> 68.611806 | H16: =H14*H15 -> 44.875677 | I16: =I14*I15 -> 40.202731 | J16: =J14*J15 -> 30.118883 | ... L16: =L14*L15 -> 17.807281
A17: Cumulative DCF ($MM) | C17: =C16 -> -96.349819 | D17: =C17+D16 -> -10.749117 | E17: =D17+E16 -> 99.881987 | F17: =E17+F16 -> 187.90535 | G17: =F17+G16 -> 256.51715 | H17: =G17+H16 -> 301.39283 | I17: =H17+I16 -> 341.59556 | J17: =I17+J16 -> 371.71444 | K17: =J17+K16 -> 395.19885 | L17: =K17+L16 -> 413.00613
A19: NPV ($MM) | C19: =SUM(C16:L16) -> 413.00613
A20: NPV, NPV function ($MM) | C20: =NPV(DiscountRate,C14:L14) -> 413.00613
A21: IRR | C21: =IRR(C14:L14) -> 1.0973625

Sheet Calc_old
A1: Old NPV check
A3: NPV at 8% ($MM) | B3: =NPV(0.08,Cashflow!C14:L14) -> 457.27705
